MANIFEST.in
README.md
requirements.txt
setup.py
exam_scheduler/__init__.py
exam_scheduler/configurations.py
exam_scheduler/constants.py
exam_scheduler/main.py
exam_scheduler/output.py
exam_scheduler/parser.py
exam_scheduler/priority_queue.py
exam_scheduler/room.py
exam_scheduler/scheduler.py
exam_scheduler/session.py
exam_scheduler/teacher.py
exam_scheduler/util.py
exam_scheduler/verifier.py
exam_scheduler/work_ratio.py
exam_scheduler.egg-info/PKG-INFO
exam_scheduler.egg-info/SOURCES.txt
exam_scheduler.egg-info/dependency_links.txt
exam_scheduler.egg-info/entry_points.txt
exam_scheduler.egg-info/requires.txt
exam_scheduler.egg-info/top_level.txt