Metadata-Version: 2.1
Name: exam-scheduler
Version: 0.0.8
Summary: A commandline tool to create examination schedules
Home-page: http://github.com/srbcheema1/exam_scheduler
Author: Sarbjit Singh
Author-email: srbcheema1@gmail.com
License: MIT License
Platform: UNKNOWN
Classifier: Operating System :: POSIX :: Linux
Classifier: License :: OSI Approved :: MIT License
Classifier: Programming Language :: Python :: 3.5
